flopyarcade/__init__.py
flopyarcade/flopyarcade.py
flopyarcade/play.py
flopyarcade/play_againstai.py
flopyarcade/train_dqn.py
flopyarcade/train_neuroevolution.py
flopyarcade/train_rllib2_apexdqn.py
flopyarcade/train_rllib_apexdqn.py
flopyarcade/train_rllib_appo.py
flopyarcade/train_rllib_appo2.py
flopyarcade/train_rllib_impala.py
flopyarcade/train_rllib_ppo.py
flopyarcade/examples/policymodels/1s-d/.is_checkpoint
flopyarcade/examples/policymodels/1s-d/1s-d
flopyarcade/examples/policymodels/1s-d/1s-d.tune_metadata
flopyarcade/examples/policymodels/2s-d/.is_checkpoint
flopyarcade/examples/policymodels/2s-d/2s-d
flopyarcade/examples/policymodels/2s-d/2s-d.tune_metadata
flopyarcade/examples/policymodels/3s-d/.is_checkpoint
flopyarcade/examples/policymodels/3s-d/3s-d
flopyarcade/examples/policymodels/3s-d/3s-d.tune_metadata
flopyarcade/simulators/simulators_linux.zip
flopyarcade/simulators/simulators_mac.zip
flopyarcade/simulators/simulators_win32.zip
flopyarcade/simulators/simulators_win64.zip
flopyarcade/tests/__init__.py
flopyarcade/tests/test_agent_dqn.py
flopyarcade/tests/test_agent_neuroevolution.py
flopyarcade/tests/test_play.py
flopyarcade-0.6.18.dist-info/licenses/LICENSE
flopyarcade-0.6.18.dist-info/METADATA
flopyarcade-0.6.18.dist-info/WHEEL
flopyarcade-0.6.18.dist-info/top_level.txt
flopyarcade-0.6.18.dist-info/RECORD
