Metadata-Version: 2.4
Name: flopyarcade
Version: 0.6.18
Summary: Simulated groundwater flow environments for reinforcement learning.
Home-page: https://github.com/philipphoehn/flopyarcade
Author: Philipp Hoehn
Author-email: Philipp Hoehn <philipp.hoehn@yahoo.com>
License: GNU GPLv3
Project-URL: Homepage, https://github.com/philipphoehn/flopyarcade
Project-URL: Documentation, https://flopyarcade.readthedocs.io
Classifier: Development Status :: 3 - Alpha
Classifier: Intended Audience :: Science/Research
Classifier: Intended Audience :: Education
Classifier: Intended Audience :: Developers
Classifier: License :: OSI Approved :: GNU General Public License v3 (GPLv3)
Classifier: Natural Language :: English
Classifier: Operating System :: POSIX :: Linux
Classifier: Operating System :: Microsoft :: Windows
Classifier: Programming Language :: Python :: 3
Classifier: Programming Language :: Python :: 3 :: Only
Classifier: Topic :: Scientific/Engineering
Classifier: Topic :: Scientific/Engineering :: Hydrology
Classifier: Topic :: Scientific/Engineering :: Artificial Intelligence
Classifier: Topic :: Education
Requires-Python: <=3.12,>=3.7
License-File: LICENSE
Requires-Dist: coverage
Requires-Dist: flopy>=3.9.2
Requires-Dist: gymnasium>=0.29.1
Requires-Dist: imageio>=2.22.4
Requires-Dist: ipython>=7.34.0
Requires-Dist: joblib>=1.2.0
Requires-Dist: lz4>=4.0.2
Requires-Dist: matplotlib>=3.6.2
Requires-Dist: importlib-metadata>=4.13.0
Requires-Dist: numpy>=2.1.3
Requires-Dist: pandas>=1.5.2
Requires-Dist: pathos>=0.3.0
Requires-Dist: pillow>=9.3.0
Requires-Dist: pygame>=2.1.2
Requires-Dist: ray[all]==2.43.0
Requires-Dist: ray[tune]==2.43.0
Requires-Dist: ray[rllib]==2.43.0
Requires-Dist: scikit-image>=0.19.3
Requires-Dist: tensorflow>=2.11.0
Requires-Dist: tqdm>=4.64.1
Requires-Dist: xmipy==1.3.0
Dynamic: author
Dynamic: home-page
Dynamic: license-file
